pyhatodi/__init__.py
pyhatodi/cli.py
pyhatodi/commands/__init__.py
pyhatodi/commands/b64.py
pyhatodi/commands/jwt.py
pyhatodi-0.1.10.dist-info/METADATA
pyhatodi-0.1.10.dist-info/WHEEL
pyhatodi-0.1.10.dist-info/entry_points.txt
pyhatodi-0.1.10.dist-info/top_level.txt
pyhatodi-0.1.10.dist-info/RECORD
