Metadata-Version: 2.4
Name: pyhatodi
Version: 0.1.10
Summary: Toolkit for developers.
Requires-Python: >=3.13
